README.rst
setup.py
stockipy/__init__.py
stockipy/symbols.py
stockipy.egg-info/PKG-INFO
stockipy.egg-info/SOURCES.txt
stockipy.egg-info/dependency_links.txt
stockipy.egg-info/top_level.txt
tests/__init__.py
tests/test_sample.py