Metadata-Version: 1.1
Name: stockipy
Version: 0.1.0
Summary: UNKNOWN
Home-page: https://github.com/chillaranand/stockipy
Author: chillaranand
Author-email: chillar@avilpage.com
License: UNKNOWN
Platform: UNKNOWN
Classifier: Development Status :: 2 - Pre-Alpha
Classifier: Programming Language :: Python
Classifier: Programming Language :: Python :: 2
Classifier: Programming Language :: Python :: 2.7
Classifier: Programming Language :: Python :: 3
Classifier: Programming Language :: Python :: 3.4
Classifier: Programming Language :: Python :: 3.5
